MANIFEST.in
README.rst
setup.py
pyrocksdb.egg-info/PKG-INFO
pyrocksdb.egg-info/SOURCES.txt
pyrocksdb.egg-info/dependency_links.txt
pyrocksdb.egg-info/requires.txt
pyrocksdb.egg-info/top_level.txt
rocksdb/__init__.py
rocksdb/_rocksdb.cpp
rocksdb/_rocksdb.pyx
rocksdb/backup.pxd
rocksdb/cache.pxd
rocksdb/comparator.pxd
rocksdb/db.pxd
rocksdb/env.pxd
rocksdb/errors.py
rocksdb/filter_policy.pxd
rocksdb/interfaces.py
rocksdb/iterator.pxd
rocksdb/logger.pxd
rocksdb/memtablerep.pxd
rocksdb/merge_operator.pxd
rocksdb/options.pxd
rocksdb/slice_.pxd
rocksdb/slice_transform.pxd
rocksdb/snapshot.pxd
rocksdb/status.pxd
rocksdb/std_memory.pxd
rocksdb/table_factory.pxd
rocksdb/universal_compaction.pxd
rocksdb/cpp/comparator_wrapper.hpp
rocksdb/cpp/filter_policy_wrapper.hpp
rocksdb/cpp/memtable_factories.hpp
rocksdb/cpp/merge_operator_wrapper.hpp
rocksdb/cpp/slice_transform_wrapper.hpp
rocksdb/cpp/utils.hpp
rocksdb/cpp/write_batch_iter_helper.hpp
rocksdb/tests/__init__.py
rocksdb/tests/test_db.py
rocksdb/tests/test_options.py