Metadata-Version: 1.0
Name: pyrocksdb
Version: 0.4
Summary: Python bindings for RocksDB
Home-page: https://github.com/stephan-hof/pyrocksdb
Author: Stephan Hofmockel
Author-email: Use the github issues
License: BSD License
Keywords: rocksdb
Platform: UNKNOWN
